source_kyve/__init__.py
source_kyve/run.py
source_kyve/source.py
source_kyve/spec.yaml
source_kyve/stream.py
source_kyve/utils.py
airbyte_source_kyve-0.2.52.dist-info/METADATA
airbyte_source_kyve-0.2.52.dist-info/WHEEL
airbyte_source_kyve-0.2.52.dist-info/entry_points.txt
airbyte_source_kyve-0.2.52.dist-info/RECORD
