Metadata-Version: 2.1
Name: airbyte-source-kyve
Version: 0.2.52
Summary: Source implementation for KYVE.
Home-page: https://airbyte.com
License: MIT
Author: KYVE Core Team
Author-email: security@kyve.network
Requires-Python: >=3.9,<3.12
Classifier: License :: OSI Approved :: MIT License
Classifier: Programming Language :: Python :: 3
Classifier: Programming Language :: Python :: 3.9
Classifier: Programming Language :: Python :: 3.10
Classifier: Programming Language :: Python :: 3.11
Requires-Dist: airbyte-cdk (==0.80.0)
Project-URL: Documentation, https://docs.airbyte.com/integrations/sources/kyve
Project-URL: Repository, https://github.com/airbytehq/airbyte
